texttoaudio/__init__.py
texttoaudio/texttoaudio.py
texttoaudioconverter-0.1.dist-info/METADATA
texttoaudioconverter-0.1.dist-info/WHEEL
texttoaudioconverter-0.1.dist-info/top_level.txt
texttoaudioconverter-0.1.dist-info/RECORD
